riix/__init__.py
riix/eval.py
riix/metrics.py
riix/core/__init__.py
riix/core/base.py
riix/core/test.py
riix/models/__init__.py
riix/models/autograd_rating_system.py
riix/models/baselines.py
riix/models/constant_variance_glicko.py
riix/models/elo.py
riix/models/elo_davidson.py
riix/models/elomentum.py
riix/models/gen_elo.py
riix/models/glicko.py
riix/models/glicko2.py
riix/models/iterative_markov.py
riix/models/melo.py
riix/models/online_disc_decomp.py
riix/models/online_rao_kupper.py
riix/models/skf.py
riix/models/template.py
riix/models/temporal_massey.py
riix/models/trueskill.py
riix/models/velo.py
riix/models/weng_lin.py
riix/models/weng_lin_thurstone_mosteller.py
riix/models/yuksel_2024.py
riix/utils/__init__.py
riix/utils/constants.py
riix/utils/data_utils.py
riix/utils/date_utils.py
riix/utils/math_utils.py
riix-0.0.6.dist-info/LICENSE
riix-0.0.6.dist-info/METADATA
riix-0.0.6.dist-info/WHEEL
riix-0.0.6.dist-info/top_level.txt
riix-0.0.6.dist-info/RECORD
