Metadata-Version: 2.1
Name: riix
Version: 0.0.6
Summary: vectorized implementations of online rating systems
Author-email: Clayton Thorrez <claytonthorrez@gmail.com>
License: Attribution-NonCommercial-ShareAlike 4.0 International
Project-URL: Docs, https://cthorrez.github.io/riix/
Project-URL: Repository, https://github.com/cthorrez/riix
Project-URL: Issues, https://github.com/cthorrez/riix/issues
Keywords: rating system,paired comparison
License-File: LICENSE
Requires-Dist: numpy
Requires-Dist: scipy
Requires-Dist: polars
Requires-Dist: jax
